recstudio/__init__.py
recstudio/ann/__init__.py
recstudio/ann/sampler.py
recstudio/data/__init__.py
recstudio/data/advance_dataset.py
recstudio/data/dataset.py
recstudio/data/config/all.yaml
recstudio/data/config/amazon-beauty.yaml
recstudio/data/config/amazon-books.yaml
recstudio/data/config/amazon-electronics.yaml
recstudio/data/config/gowalla.yaml
recstudio/data/config/ml-100k.yaml
recstudio/data/config/ml-10m.yaml
recstudio/data/config/ml-1m.yaml
recstudio/data/config/ml-20m.yaml
recstudio/data/config/tmall.yaml
recstudio/eval/__init__.py
recstudio/model/__init__.py
recstudio/model/init.py
recstudio/model/loss_func.py
recstudio/model/ranker.py
recstudio/model/retriever.py
recstudio/model/scorer.py
recstudio/model/ae/config/all.yaml
recstudio/model/ae/config/multidae.yaml
recstudio/model/ae/config/multivae.yaml
recstudio/model/basemodel/__init__.py
recstudio/model/basemodel/basemodel.yaml
recstudio/model/basemodel/baseranker.py
recstudio/model/basemodel/baseretriever.py
recstudio/model/basemodel/recommender.py
recstudio/model/fm/__init__.py
recstudio/model/fm/dcn.py
recstudio/model/fm/deepfm.py
recstudio/model/fm/fm.py
recstudio/model/fm/lr.py
recstudio/model/fm/nfm.py
recstudio/model/fm/config/all.yaml
recstudio/model/fm/config/dcn.yaml
recstudio/model/fm/config/deepfm.yaml
recstudio/model/fm/config/fm.yaml
recstudio/model/fm/config/lr.yaml
recstudio/model/fm/config/nfm.yaml
recstudio/model/graph/__init__.py
recstudio/model/graph/lightgcn.py
recstudio/model/graph/ncl.py
recstudio/model/graph/ngcf.py
recstudio/model/graph/sgl.py
recstudio/model/graph/simgcl.py
recstudio/model/graph/config/all.yaml
recstudio/model/graph/config/lightgcn.yaml
recstudio/model/graph/config/ncl.yaml
recstudio/model/graph/config/ngcf.yaml
recstudio/model/graph/config/sgl.yaml
recstudio/model/graph/config/simgcl.yaml
recstudio/model/mf/__init__.py
recstudio/model/mf/bpr.py
recstudio/model/mf/cml.py
recstudio/model/mf/dssm.py
recstudio/model/mf/ease.py
recstudio/model/mf/irgan.py
recstudio-0.0.2a1.dist-info/LICENSE
recstudio-0.0.2a1.dist-info/METADATA
recstudio-0.0.2a1.dist-info/WHEEL
recstudio-0.0.2a1.dist-info/top_level.txt
recstudio-0.0.2a1.dist-info/RECORD
